LICENSE.txt
MANIFEST.in
README.rst
setup.py
between/__init__.py
between/bot.py
between/client.py
between/exceptions.py
between/models.py
between/preloads.py
between/utils.py
between.egg-info/PKG-INFO
between.egg-info/SOURCES.txt
between.egg-info/dependency_links.txt
between.egg-info/pbr.json
between.egg-info/requires.txt
between.egg-info/top_level.txt
between.egg-info/zip-safe